{
   "type": "postgres",
   "host": "localhost",
   "port": 5433,
   "username": "postgres",
   "password": "root",
   "database": "test",
   "synchronize": true,
   "logging": false,
   "entities": [
      "src/entities/**/*{.ts,.js}"
   ],
   "migrations": [
      "dist/database/migration/**/*.js"
   ],
   "subscribers": [
      "dist/subscriber/**/*.js"
   ],
   "cli": {
      "entitiesDir": "src/entities",
      "migrationsDir": "src/migration",
      "subscribersDir": "src/subscriber"
   },
   "seeds": [
      "src/database/seeds/**/*{.ts,.js}"
   ],
   "factories": [
      "src/database/factories/**/*{.ts,.js}"
   ]
}